{"2021-09-15T11_29_39": {"D4:20:B0:A9:33:F2": {"frequency": "2.412", "frequency_units": "GHz", "channel": "1", "signal_quality": "38", "signal_total": "70", "signal_level_dBm": "-72", "essid": "eduroam"}, "D4:20:B0:A9:33:F3": {"frequency": "2.412", "frequency_units": "GHz", "channel": "1", "signal_quality": "41", "signal_total": "70", "signal_level_dBm": "-69", "essid": "MIT"}, "44:E4:D9:BD:22:F5": {"frequency": "2.412", "frequency_units": "GHz", "channel": "1", "signal_quality": "41", "signal_total": "70", "signal_level_dBm": "-69", "essid": "BU Guest (unencrypted)"}, "44:E4:D9:BD:22:F2": {"frequency": "2.412", "frequency_units": "GHz", "channel": "1", "signal_quality": "39", "signal_total": "70", "signal_level_dBm": "-71", "essid": "BU (802.1x)"}, "44:E4:D9:BD:22:F7": {"frequency": "2.412", "frequency_units": "GHz", "channel": "1", "signal_quality": "40", "signal_total": "70", "signal_level_dBm": "-70", "essid": "BU (requires VPN)"}, "14:58:D0:FD:A0:B6": {"frequency": "2.437", "frequency_units": "GHz", "channel": "6", "signal_quality": "50", "signal_total": "70", "signal_level_dBm": "-60", "essid": "HP-Print-B6-ENVY 4500 series"}, "44:E4:D9:BD:23:04": {"frequency": "2.437", "frequency_units": "GHz", "channel": "6", "signal_quality": "43", "signal_total": "70", "signal_level_dBm": "-67", "essid": "eduroam"}, "44:E4:D9:BD:23:07": {"frequency": "2.437", "frequency_units": "GHz", "channel": "6", "signal_quality": "43", "signal_total": "70", "signal_level_dBm": "-67", "essid": "BU (requires VPN)"}, "44:E4:D9:BD:23:05": {"frequency": "2.437", "frequency_units": "GHz", "channel": "6", "signal_quality": "43", "signal_total": "70", "signal_level_dBm": "-67", "essid": "BU Guest (unencrypted)"}, "44:E4:D9:BD:23:02": {"frequency": "2.437", "frequency_units": "GHz", "channel": "6", "signal_quality": "43", "signal_total": "70", "signal_level_dBm": "-67", "essid": "BU (802.1x)"}, "FA:8F:CA:38:E4:3A": {"frequency": "2.437", "frequency_units": "GHz", "channel": "6", "signal_quality": "31", "signal_total": "70", "signal_level_dBm": "-79", "essid": "Bedroom speaker.o"}, "6C:CD:D6:01:C8:3E": {"frequency": "2.442", "frequency_units": "GHz", "channel": "7", "signal_quality": "33", "signal_total": "70", "signal_level_dBm": "-77", "essid": "YESBOSTON2"}, "5C:71:0D:6D:D8:CD": {"frequency": "5.32", "frequency_units": "GHz", "channel": "64", "signal_quality": "38", "signal_total": "70", "signal_level_dBm": "-72", "essid": "BU (requires VPN)"}, "5C:71:0D:6D:D8:CE": {"frequency": "5.32", "frequency_units": "GHz", "channel": "64", "signal_quality": "37", "signal_total": "70", "signal_level_dBm": "-73", "essid": "BU Guest (unencrypted)"}, "5C:71:0D:6D:D8:CF": {"frequency": "5.32", "frequency_units": "GHz", "channel": "64", "signal_quality": "37", "signal_total": "70", "signal_level_dBm": "-73", "essid": "BU (802.1x)"}, "44:E4:D9:BD:22:F4": {"frequency": "2.412", "frequency_units": "GHz", "channel": "1", "signal_quality": "40", "signal_total": "70", "signal_level_dBm": "-70", "essid": "eduroam"}, "4C:C5:3E:AB:E9:4E": {"frequency": "2.437", "frequency_units": "GHz", "channel": "6", "signal_quality": "32", "signal_total": "70", "signal_level_dBm": "-78", "essid": "Starry09160"}, "5C:71:0D:6D:D8:C0": {"frequency": "2.412", "frequency_units": "GHz", "channel": "1", "signal_quality": "36", "signal_total": "70", "signal_level_dBm": "-74", "essid": "BU (802.1x)"}, "C0:62:6B:E5:84:74": {"frequency": "2.462", "frequency_units": "GHz", "channel": "11", "signal_quality": "37", "signal_total": "70", "signal_level_dBm": "-73", "essid": "eduroam"}, "44:1C:12:EC:2E:FA": {"frequency": "2.412", "frequency_units": "GHz", "channel": "1", "signal_quality": "34", "signal_total": "70", "signal_level_dBm": "-76", "essid": ""}, "D4:20:B0:A9:33:F1": {"frequency": "2.412", "frequency_units": "GHz", "channel": "1", "signal_quality": "39", "signal_total": "70", "signal_level_dBm": "-71", "essid": "MIT SECURE"}, "D4:20:B0:A9:33:F4": {"frequency": "2.412", "frequency_units": "GHz", "channel": "1", "signal_quality": "41", "signal_total": "70", "signal_level_dBm": "-69", "essid": "MIT GUEST"}, "C0:62:6B:E5:84:77": {"frequency": "2.462", "frequency_units": "GHz", "channel": "11", "signal_quality": "35", "signal_total": "70", "signal_level_dBm": "-75", "essid": "BU (requires VPN)"}, "C0:62:6B:E5:84:75": {"frequency": "2.462", "frequency_units": "GHz", "channel": "11", "signal_quality": "36", "signal_total": "70", "signal_level_dBm": "-74", "essid": "BU Guest (unencrypted)"}, "70:F1:96:EF:6D:F5": {"frequency": "2.462", "frequency_units": "GHz", "channel": "11", "signal_quality": "28", "signal_total": "70", "signal_level_dBm": "-82", "essid": "SwaySpa"}, "62:45:B0:30:30:4F": {"frequency": "5.2", "frequency_units": "GHz", "channel": "40", "signal_quality": "32", "signal_total": "70", "signal_level_dBm": "-78", "essid": ""}, "5C:71:0D:6D:D8:C1": {"frequency": "2.412", "frequency_units": "GHz", "channel": "1", "signal_quality": "37", "signal_total": "70", "signal_level_dBm": "-73", "essid": "BU Guest (unencrypted)"}, "5C:71:0D:6D:D8:C2": {"frequency": "2.412", "frequency_units": "GHz", "channel": "1", "signal_quality": "36", "signal_total": "70", "signal_level_dBm": "-74", "essid": "BU (requires VPN)"}, "44:1C:12:EC:2E:FC": {"frequency": "2.412", "frequency_units": "GHz", "channel": "1", "signal_quality": "34", "signal_total": "70", "signal_level_dBm": "-76", "essid": ""}, "98:0D:67:F2:56:60": {"frequency": "2.462", "frequency_units": "GHz", "channel": "11", "signal_quality": "38", "signal_total": "70", "signal_level_dBm": "-72", "essid": "FocusedExplorer"}}}
